dataall_sdk/__init__.py
dataall_sdk/__metadata__.py
dataall_sdk/utils/__init__.py
dataall_sdk/utils/waiter_functions.py
dataall_sdk-0.4.3.dist-info/METADATA
dataall_sdk-0.4.3.dist-info/WHEEL
dataall_sdk-0.4.3.dist-info/licenses/LICENSE
dataall_sdk-0.4.3.dist-info/licenses/NOTICE
dataall_sdk-0.4.3.dist-info/licenses/NOTICE.txt
dataall_sdk-0.4.3.dist-info/RECORD
