Metadata-Version: 2.4
Name: dataall-sdk
Version: 0.4.3
Summary: AWS data.all SDK
License: Apache-2.0
License-File: LICENSE
License-File: NOTICE
License-File: NOTICE.txt
Keywords: dataall,aws
Author: Amazon Web Services
Requires-Python: >=3.9, <4.0
Classifier: Programming Language :: Python :: 3.9
Classifier: Programming Language :: Python :: 3.10
Classifier: Programming Language :: Python :: 3.11
Classifier: Programming Language :: Python :: 3.12
Requires-Dist: boto3 (>=1.28.22,<2.0.0)
Requires-Dist: botocore (>=1.31.22,<2.0.0)
Requires-Dist: build (>=0.10.0,<1.0.0)
Requires-Dist: dataall-core (>=0.4.3)
Requires-Dist: packaging (>=24.2)
Requires-Dist: setuptools ; python_version >= "3.12"
Requires-Dist: typing-extensions (>=4.4.0,<5.0.0)
